{
	"configurations" : 
	[
		{
			"directories" : 
			[
				{
					"build" : ".",
					"jsonFile" : "directory-.-Debug-f5ebdc15457944623624.json",
					"minimumCMakeVersion" : 
					{
						"string" : "3.30"
					},
					"projectIndex" : 0,
					"source" : ".",
					"targetIndexes" : 
					[
						0
					]
				}
			],
			"name" : "Debug",
			"projects" : 
			[
				{
					"directoryIndexes" : 
					[
						0
					],
					"name" : "tp",
					"targetIndexes" : 
					[
						0
					]
				}
			],
			"targets" : 
			[
				{
					"directoryIndex" : 0,
					"id" : "tp::@6890427a1f51a3e7e1df",
					"jsonFile" : "target-tp-Debug-849fd82e4ecde9017966.json",
					"name" : "tp",
					"projectIndex" : 0
				}
			]
		}
	],
	"kind" : "codemodel",
	"paths" : 
	{
		"build" : "/home/tsiory/Documents/cours_1\u00e8_ann\u00e9e_ingenieur/c++_poo/tp/cmake-build-debug",
		"source" : "/home/tsiory/Documents/cours_1\u00e8_ann\u00e9e_ingenieur/c++_poo/tp"
	},
	"version" : 
	{
		"major" : 2,
		"minor" : 7
	}
}
